generic_service_bus_cqrs/__init__.py
generic_service_bus_cqrs/builder.py
generic_service_bus_cqrs/domain.py
generic_service_bus_cqrs/enum_type.py
generic_service_bus_cqrs/interfaces.py
generic_service_bus_cqrs/options.py
generic_service_bus_cqrs/redis_service_bus.py
generic_service_bus_cqrs-0.1.2.dist-info/METADATA
generic_service_bus_cqrs-0.1.2.dist-info/WHEEL
generic_service_bus_cqrs-0.1.2.dist-info/top_level.txt
generic_service_bus_cqrs-0.1.2.dist-info/RECORD
